_netifaces.cpython-311-darwin.so
netifaces_plus-0.12.4.dist-info/RECORD
netifaces_plus-0.12.4.dist-info/LICENSE
netifaces_plus-0.12.4.dist-info/WHEEL
netifaces_plus-0.12.4.dist-info/top_level.txt
netifaces_plus-0.12.4.dist-info/METADATA
netifaces/__init__.pyi
netifaces/__init__.py
netifaces/py.typed
